MANIFEST.in
README.md
setup.py
bylaws/__init__.py
bylaws/admin.py
bylaws/forms.py
bylaws/managers.py
bylaws/models.py
bylaws/urls.py
bylaws/views.py
bylaws/templates/bylaws/.base.html.swp
bylaws/templates/bylaws/.bylaws_detail.html.swp
bylaws/templates/bylaws/base.html
bylaws/templates/bylaws/bylaws_detail.html
bylaws/utils/.diff.py.swp
bylaws/utils/__init__.py
bylaws/utils/__init__.pyc
bylaws/utils/diff.py
bylaws/utils/diff.pyc
django_bylaws.egg-info/PKG-INFO
django_bylaws.egg-info/SOURCES.txt
django_bylaws.egg-info/dependency_links.txt
django_bylaws.egg-info/requires.txt
django_bylaws.egg-info/top_level.txt
django_bylaws.egg-info/zip-safe